{
  "hash": "6c83f5bb",
  "configHash": "5d677169",
  "lockfileHash": "0711f664",
  "browserHash": "71643b0a",
  "optimized": {
    "firebase/firestore": {
      "src": "../../node_modules/firebase/firestore/dist/esm/index.esm.js",
      "file": "firebase_firestore.js",
      "fileHash": "b4fa5b43",
      "needsInterop": false
    },
    "react-dom/client": {
      "src": "../../node_modules/react-dom/client.js",
      "file": "react-dom_client.js",
      "fileHash": "ec1898f0",
      "needsInterop": true
    },
    "react-router-dom": {
      "src": "../../node_modules/react-router-dom/dist/index.js",
      "file": "react-router-dom.js",
      "fileHash": "4bd31a08",
      "needsInterop": false
    },
    "react": {
      "src": "../../node_modules/react/index.js",
      "file": "react.js",
      "fileHash": "bd9d9660",
      "needsInterop": true
    },
    "react/jsx-dev-runtime": {
      "src": "../../node_modules/react/jsx-dev-runtime.js",
      "file": "react_jsx-dev-runtime.js",
      "fileHash": "e6338bdb",
      "needsInterop": true
    }
  },
  "chunks": {
    "react-TUYU05Ph": {
      "file": "react-TUYU05Ph.js",
      "isDynamicEntry": false
    },
    "react-dom-DMGCgcj7": {
      "file": "react-dom-DMGCgcj7.js",
      "isDynamicEntry": false
    }
  }
}